<?xml version="1.0" encoding="UTF-8"?>
<con:resource name="/HelloWorld" path="/HelloWorld" id="a2c68361-a644-4ee3-8719-7173fa1f5ae2" xmlns:con="http://eviware.com/soapui/config"><con:settings><con:setting id="a2c68361-a644-4ee3-8719-7173fa1f5ae2fileName">%2FHelloWorld</con:setting></con:settings><con:parameters/><con:method name="GET" id="2f5cd6cc-6f8b-4973-b861-2bbd9f996a40" method="GET"><con:description>
</con:description><con:settings/><con:parameters/><con:representation type="RESPONSE"><con:mediaType>application/json</con:mediaType><con:status>200</con:status><con:params/></con:representation><con:request name="Request 1" id="13eff2fa-6496-45be-8a00-bb25c1797d8d" mediaType="application/json"><con:settings/><con:endpoint>http://rapis02.aqa.com.ru</con:endpoint><con:parameters/></con:request></con:method></con:resource>