<?xml version="1.0" encoding="UTF-8"?>
<con:resource name="/Vse" path="/Vse" id="eea38536-2a2a-448c-a204-47280edfb5d5" xmlns:con="http://eviware.com/soapui/config"><con:settings><con:setting id="eea38536-2a2a-448c-a204-47280edfb5d5fileName">%2FVse</con:setting></con:settings><con:parameters/><con:method name="GET" id="b58e2069-f6c9-41b1-84ab-7e4a491b0cd6" method="GET"><con:description>
</con:description><con:settings/><con:parameters><con:parameter><con:name>x</con:name><con:style>QUERY</con:style><con:dataType>integer</con:dataType><con:description xsi:nil="true" xmlns:xsi="http://www.w3.org/2001/XMLSchema-instance"/></con:parameter><con:parameter><con:name>y</con:name><con:style>QUERY</con:style><con:dataType>integer</con:dataType><con:description xsi:nil="true" xmlns:xsi="http://www.w3.org/2001/XMLSchema-instance"/></con:parameter><con:parameter><con:name>z</con:name><con:style>QUERY</con:style><con:description xsi:nil="true" xmlns:xsi="http://www.w3.org/2001/XMLSchema-instance"/></con:parameter></con:parameters><con:representation type="RESPONSE"><con:mediaType>application/json</con:mediaType><con:status>200</con:status><con:params/></con:representation><con:request name="Request 1" id="70eb6d57-fb63-42d6-8d41-e02ace001bb8" mediaType="application/json"><con:settings/><con:endpoint>http://rapis02.aqa.com.ru</con:endpoint><con:parameters/></con:request></con:method></con:resource>